archai/__init__.py
archai/api/__init__.py
archai/api/dataset_provider.py
archai/api/trainer_base.py
archai/common/__init__.py
archai/common/apex_utils.py
archai/common/atomic_file_handler.py
archai/common/azureml_helper.py
archai/common/common.py
archai/common/config.py
archai/common/delimited_text.py
archai/common/deprecation_utils.py
archai/common/distributed_utils.py
archai/common/file_utils.py
archai/common/ml_perf_utils.py
archai/common/ml_utils.py
archai/common/model_summary.py
archai/common/monitor.py
archai/common/notebook_helper.py
archai/common/ordered_dict_logger.py
archai/common/ordered_dict_logger_utils.py
archai/common/stopwatch.py
archai/common/store.py
archai/common/timing.py
archai/common/utils.py
archai/common/yaml_utils.py
archai/datasets/__init__.py
archai/datasets/cv/__init__.py
archai/datasets/cv/aircraft_dataset_provider.py
archai/datasets/cv/caltech_dataset_provider.py
archai/datasets/cv/cifar_dataset_provider.py
archai/datasets/cv/cityscapes_dataset_provider.py
archai/datasets/cv/coco_dataset_provider.py
archai/datasets/cv/face_synthetics.py
archai/datasets/cv/flowers102_dataset_provider.py
archai/datasets/cv/food101_dataset_provider.py
archai/datasets/cv/image_folder_dataset_provider.py
archai/datasets/cv/imagenet_dataset_provider.py
archai/datasets/cv/mnist_dataset_provider.py
archai/datasets/cv/stanford_cars_dataset_provider.py
archai/datasets/cv/svhn_dataset_provider.py
archai/datasets/cv/tensorpack_lmdb_dataset_provider.py
archai/datasets/cv/tensorpack_lmdb_dataset_provider_utils.py
archai/datasets/cv/usps_dataset_provider.py
archai/datasets/cv/transforms/__init__.py
archai/datasets/cv/transforms/brightness.py
archai/datasets/cv/transforms/custom_cutout.py
archai/datasets/cv/transforms/lighting.py
archai/datasets/nlp/__init__.py
archai/datasets/nlp/fast_hf_dataset_provider.py
archai/datasets/nlp/fast_hf_dataset_provider_utils.py
archai/datasets/nlp/hf_dataset_provider.py
archai/datasets/nlp/hf_dataset_provider_utils.py
archai-1.0.0.dist-info/AUTHORS.md
archai-1.0.0.dist-info/LICENSE
archai-1.0.0.dist-info/METADATA
archai-1.0.0.dist-info/NOTICE.md
archai-1.0.0.dist-info/WHEEL
archai-1.0.0.dist-info/top_level.txt
archai-1.0.0.dist-info/RECORD
