Metadata-Version: 2.1
Name: archai
Version: 1.0.0
Summary: Platform for Neural Architecture Search
Home-page: https://github.com/microsoft/archai
Author: Microsoft
License: MIT
Classifier: Intended Audience :: Science/Research
Classifier: License :: OSI Approved :: MIT License
Classifier: Development Status :: 5 - Production/Stable
Classifier: Operating System :: OS Independent
Classifier: Programming Language :: Python :: 3
Classifier: Topic :: Software Development :: Libraries
Classifier: Topic :: Software Development :: Libraries :: Python Modules
License-File: LICENSE
License-File: NOTICE.md
License-File: AUTHORS.md
Requires-Dist: h5py
Requires-Dist: hyperopt
Requires-Dist: matplotlib
Requires-Dist: onnx >=1.10.2
Requires-Dist: onnxruntime >=1.10.0
Requires-Dist: overrides ==3.1.0
Requires-Dist: psutil
Requires-Dist: pyyaml
Requires-Dist: ray >=1.0.0
Requires-Dist: send2trash >=1.8.0
Requires-Dist: statopt
Requires-Dist: tensorboard
Requires-Dist: tensorwatch
Requires-Dist: tqdm
Provides-Extra: aml
Requires-Dist: azure-ai-ml ==1.5.0 ; extra == 'aml'
Requires-Dist: azure-data-tables ; extra == 'aml'
Requires-Dist: azure-identity ; extra == 'aml'
Requires-Dist: azure-storage-blob ; extra == 'aml'
Requires-Dist: azureml-mlflow ; extra == 'aml'
Requires-Dist: ipykernel ; extra == 'aml'
Requires-Dist: jupyter ; extra == 'aml'
Requires-Dist: matplotlib ; extra == 'aml'
Requires-Dist: mldesigner ; extra == 'aml'
Requires-Dist: mlflow ; extra == 'aml'
Requires-Dist: lightning >=2.0.0 ; extra == 'aml'
Requires-Dist: torchvision ; extra == 'aml'
Provides-Extra: cv
Requires-Dist: gorilla >=0.4.0 ; extra == 'cv'
Requires-Dist: opencv-python ; extra == 'cv'
Requires-Dist: lightning >=2.0.0 ; extra == 'cv'
Requires-Dist: scikit-learn ; extra == 'cv'
Requires-Dist: torchvision ; extra == 'cv'
Provides-Extra: deepspeed
Requires-Dist: deepspeed ; extra == 'deepspeed'
Requires-Dist: mlflow ; extra == 'deepspeed'
Provides-Extra: dev
Requires-Dist: gorilla >=0.4.0 ; extra == 'dev'
Requires-Dist: opencv-python ; extra == 'dev'
Requires-Dist: lightning >=2.0.0 ; extra == 'dev'
Requires-Dist: scikit-learn ; extra == 'dev'
Requires-Dist: torchvision ; extra == 'dev'
Requires-Dist: datasets >=2.4.0 ; extra == 'dev'
Requires-Dist: einops ; extra == 'dev'
Requires-Dist: opt-einsum ; extra == 'dev'
Requires-Dist: tokenizers >=0.10.3 ; extra == 'dev'
Requires-Dist: transformers ==4.27.4 ; extra == 'dev'
Requires-Dist: nbimporter ; extra == 'dev'
Requires-Dist: nbsphinx ; extra == 'dev'
Requires-Dist: nbval ; extra == 'dev'
Requires-Dist: pandas ; extra == 'dev'
Requires-Dist: pydata-sphinx-theme ==0.13.1 ; extra == 'dev'
Requires-Dist: sphinx ; extra == 'dev'
Requires-Dist: sphinx-book-theme ; extra == 'dev'
Requires-Dist: sphinx-git ; extra == 'dev'
Requires-Dist: sphinx-sitemap ; extra == 'dev'
Requires-Dist: sphinx-inline-tabs ; extra == 'dev'
Requires-Dist: sphinxcontrib-programoutput ; extra == 'dev'
Requires-Dist: sphinxcontrib-mermaid ; extra == 'dev'
Requires-Dist: azure-data-tables ; extra == 'dev'
Requires-Dist: azure-identity ; extra == 'dev'
Requires-Dist: azure-storage-blob ; extra == 'dev'
Requires-Dist: flake8 >=5.0.4 ; extra == 'dev'
Requires-Dist: pytest ; extra == 'dev'
Requires-Dist: tk ; extra == 'dev'
Requires-Dist: azure-ai-ml ==1.5.0 ; extra == 'dev'
Requires-Dist: azureml-mlflow ; extra == 'dev'
Requires-Dist: ipykernel ; extra == 'dev'
Requires-Dist: jupyter ; extra == 'dev'
Requires-Dist: matplotlib ; extra == 'dev'
Requires-Dist: mldesigner ; extra == 'dev'
Requires-Dist: mlflow ; extra == 'dev'
Requires-Dist: torchinfo ; extra == 'dev'
Requires-Dist: xformers ; extra == 'dev'
Requires-Dist: deepspeed ; extra == 'dev'
Provides-Extra: docs
Requires-Dist: nbimporter ; extra == 'docs'
Requires-Dist: nbsphinx ; extra == 'docs'
Requires-Dist: nbval ; extra == 'docs'
Requires-Dist: pandas ; extra == 'docs'
Requires-Dist: pydata-sphinx-theme ==0.13.1 ; extra == 'docs'
Requires-Dist: sphinx ; extra == 'docs'
Requires-Dist: sphinx-book-theme ; extra == 'docs'
Requires-Dist: sphinx-git ; extra == 'docs'
Requires-Dist: sphinx-sitemap ; extra == 'docs'
Requires-Dist: sphinx-inline-tabs ; extra == 'docs'
Requires-Dist: sphinxcontrib-programoutput ; extra == 'docs'
Requires-Dist: sphinxcontrib-mermaid ; extra == 'docs'
Provides-Extra: flash-attn
Requires-Dist: flash-attn ; extra == 'flash-attn'
Provides-Extra: nlp
Requires-Dist: datasets >=2.4.0 ; extra == 'nlp'
Requires-Dist: einops ; extra == 'nlp'
Requires-Dist: opt-einsum ; extra == 'nlp'
Requires-Dist: tokenizers >=0.10.3 ; extra == 'nlp'
Requires-Dist: transformers ==4.27.4 ; extra == 'nlp'
Provides-Extra: tasks
Requires-Dist: torchinfo ; extra == 'tasks'
Provides-Extra: tests
Requires-Dist: azure-data-tables ; extra == 'tests'
Requires-Dist: azure-identity ; extra == 'tests'
Requires-Dist: azure-storage-blob ; extra == 'tests'
Requires-Dist: flake8 >=5.0.4 ; extra == 'tests'
Requires-Dist: pytest ; extra == 'tests'
Requires-Dist: tk ; extra == 'tests'
Provides-Extra: xformers
Requires-Dist: xformers ; extra == 'xformers'
